[{"x": 14404, "y": 14201, "timestamp": 0}, {"x": 10881, "y": 5533, "timestamp": 60008}, {"x": 13370, "y": 2411, "timestamp": 120018}, {"x": 13304, "y": 2904, "timestamp": 180041}, {"x": 13325, "y": 4327, "timestamp": 240057}, {"x": 11818, "y": 3758, "timestamp": 300099}, {"x": 13188, "y": 2573, "timestamp": 360131}, {"x": 13438, "y": 4543, "timestamp": 420134}, {"x": 14122, "y": 4801, "timestamp": 480165}, {"x": 14009, "y": 4374, "timestamp": 540174}, {"x": 14057, "y": 4523, "timestamp": 543608}, {"x": 13048, "y": 3807, "timestamp": 600199}, {"x": 13493, "y": 3458, "timestamp": 660203}, {"x": 13304, "y": 3946, "timestamp": 671370}, {"x": 11031, "y": 3902, "timestamp": 720225}, {"x": 10356, "y": 2857, "timestamp": 722009}, {"x": 14122, "y": 6958, "timestamp": 780227}, {"x": 5445, "y": 5218, "timestamp": 825990}, {"x": 7437, "y": 8747, "timestamp": 840258}, {"x": 3832, "y": 4499, "timestamp": 870848}, {"x": 11850, "y": 12514, "timestamp": 900271}, {"x": 3954, "y": 4392, "timestamp": 935252}, {"x": 5984, "y": 9298, "timestamp": 960291}, {"x": 14172, "y": 13791, "timestamp": 1020294}, {"x": 9676, "y": 9344, "timestamp": 1080314}, {"x": 7896, "y": 7707, "timestamp": 1108892}, {"x": 7960, "y": 7692, "timestamp": 1118670}, {"x": 8694, "y": 8788, "timestamp": 1128347}, {"x": 8694, "y": 8788, "timestamp": 1140346}, {"x": 8182, "y": 7890, "timestamp": 1183788}, {"x": 6082, "y": 8723, "timestamp": 1200369}, {"x": 2088, "y": 7480, "timestamp": 1226596}, {"x": 1097, "y": 6681, "timestamp": 1233170}, {"x": 4797, "y": 9902, "timestamp": 1260401}, {"x": 8815, "y": 5855, "timestamp": 1320421}, {"x": 8427, "y": 6452, "timestamp": 1343908}, {"x": 9774, "y": 4095, "timestamp": 1380431}, {"x": 7550, "y": 7748, "timestamp": 1412670}, {"x": 7550, "y": 7748, "timestamp": 1440445}, {"x": 7521, "y": 13835, "timestamp": 1500478}, {"x": 9853, "y": 10404, "timestamp": 1560499}, {"x": 8944, "y": 4288, "timestamp": 1584318}, {"x": 11346, "y": 4213, "timestamp": 1597991}, {"x": 11346, "y": 4213, "timestamp": 1620501}, {"x": 8521, "y": 5119, "timestamp": 1680516}, {"x": 8885, "y": 4513, "timestamp": 1694192}, {"x": 5777, "y": 4941, "timestamp": 1706015}, {"x": 2794, "y": 1630, "timestamp": 1740547}, {"x": 7307, "y": 1590, "timestamp": 1763434}, {"x": 7307, "y": 1590, "timestamp": 1800560}, {"x": 9644, "y": 5972, "timestamp": 1860590}, {"x": 8680, "y": 8475, "timestamp": 1906161}, {"x": 9158, "y": 7397, "timestamp": 1920600}, {"x": 9816, "y": 7069, "timestamp": 1922483}, {"x": 8819, "y": 7602, "timestamp": 1927031}, {"x": 12563, "y": 11982, "timestamp": 1980614}, {"x": 11181, "y": 4039, "timestamp": 2008888}, {"x": 7849, "y": 8712, "timestamp": 2040635}, {"x": 3008, "y": 3010, "timestamp": 2063633}, {"x": 2597, "y": 1512, "timestamp": 2068259}, {"x": 8243, "y": 8102, "timestamp": 2100639}, {"x": 9113, "y": 9665, "timestamp": 2160653}, {"x": 3484, "y": 10121, "timestamp": 2220660}, {"x": 2370, "y": 8460, "timestamp": 2228944}, {"x": 4833, "y": 9311, "timestamp": 2236528}, {"x": 2284, "y": 7615, "timestamp": 2239665}, {"x": 1748, "y": 2270, "timestamp": 2271969}, {"x": 1583, "y": 2255, "timestamp": 2275668}, {"x": 2047, "y": 2245, "timestamp": 2280689}, {"x": 2047, "y": 2245, "timestamp": 2284752}]